asadfirstmodule/__init__.py
asadfirstmodule/add.py
asadfirstmodule/subtract.py
asadfirstmodule/extras/__init__.py
asadfirstmodule/extras/divide.py
asadfirstmodule/extras/multiply.py
asadfirstmodule-0.0.1.dist-info/METADATA
asadfirstmodule-0.0.1.dist-info/WHEEL
asadfirstmodule-0.0.1.dist-info/top_level.txt
asadfirstmodule-0.0.1.dist-info/RECORD
